chicagogogo/__init__.py
chicagogogo/main.py
chicagogogo-1.0.2.dist-info/METADATA
chicagogogo-1.0.2.dist-info/WHEEL
chicagogogo-1.0.2.dist-info/top_level.txt
chicagogogo-1.0.2.dist-info/RECORD
