Metadata-Version: 2.1
Name: chicagogogo
Version: 1.0.2
Requires-Dist: geopy
